TAGsieve/TAGsieveGui.py
TAGsieve/CleanDirtySoup.py
TAGsieve/__init__.py
TAGsieve-1.1.dist-info/metadata.json
TAGsieve-1.1.dist-info/WHEEL
TAGsieve-1.1.dist-info/top_level.txt
TAGsieve-1.1.dist-info/METADATA
TAGsieve-1.1.dist-info/DESCRIPTION.rst
TAGsieve-1.1.dist-info/RECORD
