Metadata-Version: 2.0
Name: TAGsieve
Version: 1.1
Summary: A small HTML/XML stripper GUI application.
Home-page: http://github.com/willibrord/TAGsieve
Author: Tom De Keyser
Author-email: tomdekeyser7@gmail.com
License: GPLv3
Platform: UNKNOWN
Requires-Dist: lxml
Requires-Dist: BeautifulSoup4
Requires-Dist: bleach
